expense_tracker/__init__.py
expense_tracker/expense_tracker.py
one_expense_tracker-0.0.1.dist-info/LICENSE
one_expense_tracker-0.0.1.dist-info/METADATA
one_expense_tracker-0.0.1.dist-info/WHEEL
one_expense_tracker-0.0.1.dist-info/top_level.txt
one_expense_tracker-0.0.1.dist-info/RECORD
