Metadata-Version: 2.1
Name: one-expense-tracker
Version: 0.0.1
Summary: A cli app for expense tracking
Home-page: https://github.com/NwizuEmmanuel/expense-tracker
Author: Onyeka Emmanuel Nwizu
Author-email: nwizuemmanuel200@gmail.com
Classifier: Programming Language :: Python :: 3
Classifier: License :: OSI Approved :: MIT License
Classifier: Operating System :: OS Independent
License-File: LICENSE
